HoundAnalyser/__init__.py
HoundAnalyser/__main__.py
HoundAnalyser/__version__.py
HoundAnalyser/goFetch.py
HoundAnalyser/data_hoover/__init__.py
HoundAnalyser/data_hoover/_mutant_classifier.py
HoundAnalyser/data_hoover/asmbl_finder.py
HoundAnalyser/data_hoover/coverage_analyser.py
HoundAnalyser/data_hoover/locus_finder.py
HoundAnalyser/data_hoover/main.py
HoundAnalyser/data_hoover/mutant_finder.py
HoundAnalyser/external/__init__.py
HoundAnalyser/external/plot_eteTree.py
HoundAnalyser/genoplot/__init__.py
HoundAnalyser/genoplot/plot_align.py
HoundAnalyser/helper_func/__init__.py
HoundAnalyser/helper_func/alignment_tools.py
HoundAnalyser/helper_func/assembly_utilities.py
HoundAnalyser/helper_func/contig_merger.py
HoundAnalyser/helper_func/data_organiser.py
HoundAnalyser/helper_func/ncbi.py
HoundAnalyser/helper_func/promoter_tools.py
HoundAnalyser/helper_func/rtrv_reads.py
HoundAnalyser/helper_func/sundry.py
HoundAnalyser/helper_func/unalignment_tools.py
HoundAnalyser-1.11.dist-info/LICENSE
HoundAnalyser-1.11.dist-info/METADATA
HoundAnalyser-1.11.dist-info/WHEEL
HoundAnalyser-1.11.dist-info/entry_points.txt
HoundAnalyser-1.11.dist-info/top_level.txt
HoundAnalyser-1.11.dist-info/RECORD
