Metadata-Version: 2.1
Name: HoundAnalyser
Version: 1.11
Summary: HOUND
Author: Carlos Reding
Author-email: carlos.reding@bristol.ac.uk
Project-URL: Source, https://gitlab.com/rc-reding/software/-/tree/main/Hound?ref_type=heads
Project-URL: Homepage, https://gitlab.com/rc-reding/software/-/tree/main/Hound?ref_type=heads
Classifier: Development Status :: 5 - Production/Stable
Classifier: Environment :: Console
Classifier: Operating System :: POSIX :: Linux
Classifier: Operating System :: MacOS
Classifier: Intended Audience :: Science/Research
Classifier: License :: OSI Approved :: GNU Lesser General Public License v2 or later (LGPLv2+)
Classifier: Programming Language :: Python :: 3
Classifier: Topic :: Adaptive Technologies
Requires-Python: >=3.9
License-File: LICENSE
Requires-Dist: PyQt5
Requires-Dist: matplotlib
Requires-Dist: ete3 <4
Requires-Dist: pyopengl
Requires-Dist: tk-tools
Requires-Dist: numpy
Requires-Dist: biopython
Requires-Dist: openpyxl
Requires-Dist: pycairo
Requires-Dist: psutil
